tests/__init__.py
tests/test_core.py
zeroskids/__init__.py
zeroskids/cli.py
zeroskids/core.py
zeroskids/obfuscator.py
zeroskids/utils.py
zeroskids-1.5.3.dist-info/licenses/LICENSE
zeroskids-1.5.3.dist-info/METADATA
zeroskids-1.5.3.dist-info/WHEEL
zeroskids-1.5.3.dist-info/top_level.txt
zeroskids-1.5.3.dist-info/RECORD
