Metadata-Version: 2.4
Name: zeroskids
Version: 1.5.3
Summary: Truly skid-proof Python obfuscator
Home-page: https://github.com/SkitDev/ZeroSkids
Author: SkitDev
Classifier: Programming Language :: Python :: 3
Classifier: Operating System :: OS Independent
Requires-Python: >=3.8
License-File: LICENSE
Dynamic: author
Dynamic: classifier
Dynamic: description
Dynamic: description-content-type
Dynamic: home-page
Dynamic: license-file
Dynamic: requires-python
Dynamic: summary
